django_utk/__init__.py
django_utk/db/__init__.py
django_utk/db/models/__init__.py
django_utk/db/models/base.py
django_utk/db/models/meta.py
django_utk/db/models/utils.py
django_utk/db/models/dbview/__init__.py
django_utk/db/models/dbview/managers.py
django_utk/db/models/dbview/mixins.py
django_utk/db/models/dbview/models.py
django_utk/db/models/dbview/querysets.py
django_utk/db/models/fix/__init__.py
django_utk/db/models/fix/delete_using_manager.py
django_utk/db/models/softdelete/__init__.py
django_utk/db/models/softdelete/managers.py
django_utk/db/models/softdelete/models.py
django_utk/db/models/softdelete/querysets.py
django_utk/db/models/timestamped/__init__.py
django_utk/db/models/timestamped/fields.py
django_utk/db/models/timestamped/managers.py
django_utk/db/models/timestamped/models.py
django_utk/db/models/timestamped/querysets.py
django_utk/misc/__init__.py
django_utk/misc/singleton.py
django_utk/tests/__init__.py
django_utk/tests/factories/__init__.py
django_utk/tests/factories/factories.py
django_utk/tests/factories/utils.py
django_utk/tests/faker/__init__.py
django_utk/tests/faker/base.py
django_utk/tests/faker/byteslike.py
django_utk/tests/faker/choices.py
django_utk/tests/faker/hashes.py
django_utk/tests/faker/iterable.py
django_utk/tests/faker/numeric.py
django_utk/tests/faker/ranges.py
django_utk/tests/faker/sequences.py
django_utk/tests/faker/strings.py
django_utk/tests/faker/uuid.py
django_utk/tests/utils/__init__.py
django_utk/tests/utils/run_n_times.py
django_utk/utils/__init__.py
django_utk/utils/args.py
django_utk/utils/env.py
django_utk/utils/importutil.py
django_utk/utils/lazy.py
django_utk/utils/popattr.py
django_utk/utils/typehint.py
django_utk/validators/__init__.py
django_utk/validators/base.py
django_utk/validators/hashes.py
django_utk/validators/uuid.py
django_utk-1.2.11.dist-info/METADATA
django_utk-1.2.11.dist-info/WHEEL
django_utk-1.2.11.dist-info/licenses/LICENSE
django_utk-1.2.11.dist-info/RECORD
