Metadata-Version: 2.3
Name: django-utk
Version: 1.2.11
Summary: The most useful tools for any django project
Project-URL: Homepage, https://github.com/v1a0/django-utk
Project-URL: Issues, https://github.com/v1a0/django-utk/issues
Author-email: v1a0 <contact@v1a0.dev>
License:                     GNU GENERAL PUBLIC LICENSE
License-File: LICENSE
Keywords: feed,reader,tutorial
Classifier: Framework :: Django
Classifier: License :: OSI Approved :: GNU General Public License v3 (GPLv3)
Classifier: Programming Language :: Python :: 3
Requires-Python: >=3.8
Requires-Dist: django>=4.0.0
Provides-Extra: dev
Requires-Dist: black; extra == 'dev'
Requires-Dist: bumpver; extra == 'dev'
Requires-Dist: isort; extra == 'dev'
Requires-Dist: pip-tools; extra == 'dev'
